{
  "dependencies": {
    "storage1": {
      "resourceId": "/subscriptions/[parameters('subscriptionId')]/resourceGroups/[parameters('resourceGroupName')]/providers/Microsoft.Storage/storageAccounts/sadhanafunxb4hqgs72bwjk",
      "type": "storage.azure",
      "connectionId": "AzureWebJobsStorage"
    },
    "appInsights1": {
      "secretStore": "AzureAppSettings",
      "resourceId": "/subscriptions/[parameters('subscriptionId')]/resourceGroups/[parameters('resourceGroupName')]/providers/microsoft.insights/components/sadhanafunction3appxb4hqgs72bwjk",
      "type": "appInsights.azure",
      "connectionId": "APPINSIGHTS_CONNECTIONSTRING"
    }
  }
}